{
  "Liga Argentina": [
    {
      "link": "Go:arg1",
      "canal": "Go:TNTSports",
      "opcion1": "Go:TNTSports",
      "opcion2": "Go:TNTSports",
      "opcion3": "Go:TNTSports",
      "torneo": "Liga Argentina 游뷣릖",
      "equipo1": "Platense",
      "equipo2": "Rosario Central",
      "fechaInicio": "2025-04-15T20:00",
      "fecha": "15 de Abril"
    }
  ],
  "Champions League": [
    {
      "link": "go:cham1",
      "canal": "Go:espn",
      "opcion1": "ESPN Argentina",
      "opcion2": "Disney+ Argentina",
      "opcion3": "ESPN2 Colombia",
      "torneo": "Champions League",
      "equipo1": "Aston Villa",
      "equipo2": "PSG",
      "fechaInicio": "2025-04-15T16:00",
      "fecha": "15 de Abril"
    },
    {
      "link": "go:cham2",
      "canal": "Go:foxsports",
      "opcion1": "Fox Sports Argentina",
      "opcion2": "Disney+ Argentina",
      "opcion3": "ESPN Colombia",
      "torneo": "Champions League",
      "equipo1": "Dortmund",
      "equipo2": "Barcelona",
      "fechaInicio": "2025-04-15T16:00",
      "fecha": "15 de Abril"
    }
  ],
  "Liga Brasile침a": [
    {
      "link": "Go:bra1",
      "canal": null,
      "opcion1": "Premiere",
      "opcion2": "Zapping",
      "opcion3": "Amazon Prime Video",
      "torneo": "Liga Brasile침a 游游",
      "equipo1": "Cear치",
      "equipo2": "Vasco da Gama",
      "fechaInicio": "2025-04-15T21:30",
      "fecha": "15 de Abril"
    }
  ],
  "Liga Colombiana": [
    {
      "link": "Go:col1",
      "canal": "Go:winplus",
      "opcion1": "Win+ Futbol",
      "opcion2": "Win Play",
      "opcion3": "ViX",
      "torneo": "Liga Colombiana 游뻟릖",
      "equipo1": "Alianza Petro.",
      "equipo2": "Dep. Pasto",
      "fechaInicio": "2025-04-15T18:00",
      "fecha": "15 de Abril"
    },
    {
      "link": "Go:col2",
      "canal": "Go:winplus",
      "opcion1": "Win Sports",
      "opcion2": "Win+ Futbol",
      "opcion3": "Win Play",
      "torneo": "Liga Colombiana 游뻟릖",
      "equipo1": "Dep. Pereira",
      "equipo2": "Dep. Cali",
      "fechaInicio": "2025-04-15T20:15",
      "fecha": "15 de Abril"
    },
    {
      "link": "Go:col3",
      "canal": "Go:winplus",
      "opcion1": "Win+ Futbol",
      "opcion2": "Win Play",
      "opcion3": "Fanatiz USA",
      "torneo": "Liga Colombiana 游뻟릖",
      "equipo1": "Tolima",
      "equipo2": "Junior",
      "fechaInicio": "2025-04-15T22:30",
      "fecha": "15 de Abril"
    }
  ],
  "Liga Ecuatoriana": [
    {
      "link": "Go:ecu1",
      "canal": null,
      "opcion1": "Canal del Futbol",
      "opcion2": "Zapping",
      "opcion3": null,
      "torneo": "Liga Ecuatoriana 游쀯릖",
      "equipo1": "Aucas",
      "equipo2": "U. Cat칩lica",
      "fechaInicio": "2025-04-15T21:00",
      "fecha": "15 de Abril"
    }
  ],
  "Liga Mexicana": [
    {
      "link": "Go:mex1",
      "canal": "Go:TUDN",
      "opcion1": "TUDN USA",
      "opcion2": "TUDN.com",
      "opcion3": "TUDN App",
      "torneo": "Liga Mexicana 游쓇릖",
      "equipo1": "Pachuca",
      "equipo2": "Tigres",
      "fechaInicio": "2025-04-15T22:00",
      "fecha": "15 de Abril"
    },
    {
      "link": "Go:mex2",
      "canal": null,
      "opcion1": "fuboTV",
      "opcion2": "UNIVERSO",
      "opcion3": "UNIVERSO NOW",
      "torneo": "Liga Mexicana 游쓇릖",
      "equipo1": "Guadalajara",
      "equipo2": "Puebla",
      "fechaInicio": "2025-04-15T22:05",
      "fecha": "15 de Abril"
    }
  ]
}
