{
  "La Liga": [
    {
      "link": "go:laliga1",
      "canal": "Go:espn",
      "opcion1": "Go:espn",
      "opcion2": "Go:espn",
      "opcion3": "Go:espn",
      "torneo": "La Liga 🇪🇸",
      "equipo1": "Osasuna",
      "equipo2": "Sevilla",
      "fechaInicio": "2025-04-24T17:00Z",
      "fecha": "24 de Abril"
    },
    {
      "link": "go:laliga2",
      "canal": "Go:Dsports",
      "opcion1": "Go:Dsports",
      "opcion2": "Go:Dsports",
      "opcion3": "Go:Dsports",
      "torneo": "La Liga 🇪🇸",
      "equipo1": "Leganés",
      "equipo2": "Girona",
      "fechaInicio": "2025-04-24T17:00Z",
      "fecha": "24 de Abril"
    },
    {
      "link": "go:laliga3",
      "canal": "Go:Dsports",
      "opcion1": "Go:Dsports",
      "opcion2": "Go:Dsports",
      "opcion3": "Go:Dsports",
      "torneo": "La Liga 🇪🇸",
      "equipo1": "Real Betis",
      "equipo2": "Real Valladolid",
      "fechaInicio": "2025-04-24T19:30Z",
      "fecha": "24 de Abril"
    },
    {
      "link": "go:laliga4",
      "canal": "Go:Dsports",
      "opcion1": "Go:Dsports",
      "opcion2": "Go:Dsports",
      "opcion3": "Go:Dsports",
      "torneo": "La Liga 🇪🇸",
      "equipo1": "Atl. Madrid",
      "equipo2": "Rayo Vallecano",
      "fechaInicio": "2025-04-24T19:30Z",
      "fecha": "24 de Abril"
    }
  ],
  "Copa Italiana": [
    {
      "link": "Go:rey1",
      "canal": "Go:Dsports",
      "opcion1": "Go:Dsports",
      "opcion2": "Go:Dsports",
      "opcion3": "Go:Dsports",
      "torneo": "Copa del Rey 🇮🇹",
      "equipo1": "Bologna",
      "equipo2": "Empoli",
      "fechaInicio": "2025-04-24T19:00Z",
      "fecha": "24 de Abril"
    }
  ],
  "Sudamericana": [
    {
      "link": "Go:suda1",
      "canal": "Go:espn",
      "opcion1": "Go:espn",
      "opcion2": "Go:espn",
      "opcion3": "Go:espn",
      "torneo": "Copa Sudamericana 🌎",
      "equipo1": "Godoy Cruz",
      "equipo2": "Grêmio",
      "fechaInicio": "2025-04-24T22:00Z",
      "fecha": "24 de Abril"
    },
    {
      "link": "Go:suda2",
      "canal": "Go:espn",
      "opcion1": "Go:espn",
      "opcion2": "Go:espn",
      "opcion3": "Go:espn",
      "torneo": "Copa Sudamericana 🌎",
      "equipo1": "Corinthians",
      "equipo2": "Racing",
      "fechaInicio": "2025-04-24T22:00Z",
      "fecha": "24 de Abril"
    },
    {
      "link": "Go:suda3",
      "canal": "Go:espn",
      "opcion1": "Go:espn",
      "opcion2": "Go:espn",
      "opcion3": "Go:espn",
      "torneo": "Copa Sudamericana 🌎",
      "equipo1": "Dep. Iquique",
      "equipo2": "Cienciano",
      "fechaInicio": "2025-04-25T00:30Z",
      "fecha": "25 de Abril"
    },
    {
      "link": "Go:suda4",
      "canal": "Go:Dsports",
      "opcion1": "Go:Dsports",
      "opcion2": "Go:Dsports",
      "opcion3": "Go:Dsports",
      "torneo": "Copa Sudamericana 🌎",
      "equipo1": "Palestino",
      "equipo2": "Cruzeiro",
      "fechaInicio": "2025-04-25T00:30Z",
      "fecha": "25 de Abril"
    },
    {
      "link": "Go:suda5",
      "canal": "Go:espn",
      "opcion1": "Go:espn",
      "opcion2": "Go:espn",
      "opcion3": "Go:espn",
      "torneo": "Copa Sudamericana 🌎",
      "equipo1": "U. Católica",
      "equipo2": "Def. y Justicia",
      "fechaInicio": "2025-04-25T02:00Z",
      "fecha": "25 de Abril"
    }
  ],
  "Libertadores": [
    {
      "link": "go:Lib1",
      "canal": "Go:foxsports2",
      "opcion1": "Go:foxsports2",
      "opcion2": "Go:foxsports2",
      "opcion3": "Go:foxsports2",
      "torneo": "Copa Libertadores 🌎",
      "equipo1": "Bolívar",
      "equipo2": "Palmeiras",
      "fechaInicio": "2025-04-24T22:00Z",
      "fecha": "24 de Abril"
    },
    {
      "link": "go:Lib2",
      "canal": "Go:espn",
      "opcion1": "Go:espn",
      "opcion2": "Go:espn",
      "opcion3": "Go:espn",
      "torneo": "Copa Libertadores 🌎",
      "equipo1": "Central Córdoba",
      "equipo2": "Dep. Táchira",
      "fechaInicio": "2025-04-24T22:00Z",
      "fecha": "24 de Abril"
    },
    {
      "link": "go:Lib3",
      "canal": "Go:foxsports2",
      "opcion1": "Go:foxsports2",
      "opcion2": "Go:foxsports2",
      "opcion3": "Go:foxsports2",
      "torneo": "Copa Libertadores 🌎",
      "equipo1": "Bahia",
      "equipo2": "Atl. Nacional",
      "fechaInicio": "2025-04-25T00:00Z",
      "fecha": "25 de Abril"
    },
    {
      "link": "go:Lib4",
      "canal": "Go:foxsports",
      "opcion1": "Go:foxsports",
      "opcion2": "Go:foxsports",
      "opcion3": "Go:foxsports",
      "torneo": "Copa Libertadores 🌎",
      "equipo1": "Cerro Porteño",
      "equipo2": "Sporting Cristal",
      "fechaInicio": "2025-04-25T00:30Z",
      "fecha": "25 de Abril"
    }
  ],
  "CONCACAF Champions Cup": [
    {
      "link": "go:cham1",
      "canal": "Go:espn",
      "opcion1": "Go:espn",
      "opcion2": "Go:espn",
      "opcion3": "Go:espn",
      "torneo": "CONCACAF Champions Cup 🌎",
      "equipo1": "Vancouver",
      "equipo2": "Inter Miami",
      "fechaInicio": "2025-04-25T02:30Z",
      "fecha": "25 de Abril"
    }
  ]
}
